README.md
setup.py
pytmangadex/__init__.py
pytmangadex/chapter.py
pytmangadex/group.py
pytmangadex/manga.py
pytmangadex/user.py
pytmangadex.egg-info/PKG-INFO
pytmangadex.egg-info/SOURCES.txt
pytmangadex.egg-info/dependency_links.txt
pytmangadex.egg-info/not-zip-safe
pytmangadex.egg-info/requires.txt
pytmangadex.egg-info/top_level.txt