Metadata-Version: 2.1
Name: pytmangadex
Version: 1.2
Summary: an library to scrape data from mangadex.org
Home-page: https://github.com/Sibyl666/pytmangadex
Author: Sibyl666
Author-email: metinkorkmaz417@gmail.com
License: MIT
Download-URL: https://github.com/Sibyl666/pytmangadex/archive/1.2.tar.gz
Platform: UNKNOWN
